Metadata-Version: 1.1
Name: django-optimistic-lock
Version: 0.1
Summary: Offline optimistic locking for Django
Home-page: https://github.com/gavinwahl/django-optimistic-lock
Author: Gavin Wahl
Author-email: gavinwahl@gmail.com
License: BSD
Platform: UNKNOWN
Classifier: Development Status :: 4 - Beta
Classifier: Environment :: Web Environment
Classifier: Framework :: Django
Classifier: Intended Audience :: Developers
Classifier: License :: OSI Approved :: BSD License
Classifier: Programming Language :: Python
Classifier: Programming Language :: Python :: 2.7
Classifier: Programming Language :: Python :: 3.4
Classifier: Programming Language :: Python :: 3.5
